{"schema":{"fields":[{"name":"ver","type":"string"},{"name":"lc","type":"string"},{"name":"alg","type":"string"},{"name":"sp","type":"string"},{"name":"clips","type":"integer"},{"name":"uq_v","type":"integer"},{"name":"uq_s","type":"integer"},{"name":"uq_sl","type":"integer"},{"name":"dup_s","type":"integer"},{"name":"dup_sl","type":"integer"},{"name":"dur_total","type":"number"},{"name":"dur_mean","type":"number"},{"name":"dur_median","type":"number"},{"name":"dur_freq","type":"string"},{"name":"v_mean","type":"number"},{"name":"v_median","type":"number"},{"name":"v_freq","type":"string"},{"name":"s_mean","type":"number"},{"name":"s_median","type":"number"},{"name":"s_freq","type":"string"},{"name":"dem_table","type":"string"}],"pandas_version":"1.4.0"},"data":[{"ver":"9.0","lc":"myv","alg":"","sp":"validated","clips":1173,"uq_v":5,"uq_s":1170,"uq_sl":1170,"dup_s":3,"dup_sl":3,"dur_total":6633.144,"dur_mean":5.6548542199,"dur_median":5.544,"dur_freq":"0-3-132-160-183-208-171-147-97-60-12","v_mean":234.6,"v_median":198.0,"v_freq":"0-0-0-0-0-2-0-1-1-1-0-0-0-0-0-0-0","s_mean":1.0025641026,"s_median":1.0,"s_freq":"0-1167-3-0-0-0-0-0-0-0-0-0-0-0-0-0","dem_table":"0-0-0-0-0|48-0-0-0-48|416-0-0-0-416|0-0-0-0-0|0-0-0-0-0|338-0-0-0-338|0-0-0-0-0|0-0-0-0-0|0-0-0-0-0|0-0-0-371-371|802-0-0-371-1173"},{"ver":"9.0","lc":"myv","alg":"","sp":"invalidated","clips":4,"uq_v":4,"uq_s":4,"uq_sl":4,"dup_s":0,"dup_sl":0,"dur_total":25.848,"dur_mean":6.462,"dur_median":6.75,"dur_freq":"0-0-0-0-1-0-1-2-0-0-0","v_mean":1.0,"v_median":1.0,"v_freq":"4-0-0-0-0-0-0-0-0-0-0-0-0-0-0-0-0","s_mean":1.0,"s_median":1.0,"s_freq":"0-4-0-0-0-0-0-0-0-0-0-0-0-0-0-0","dem_table":"0-0-0-0-0|1-0-0-0-1|1-0-0-0-1|0-0-0-0-0|0-0-0-0-0|1-0-0-0-1|0-0-0-0-0|0-0-0-0-0|0-0-0-0-0|0-0-0-1-1|3-0-0-1-4"},{"ver":"9.0","lc":"myv","alg":"","sp":"other","clips":324,"uq_v":5,"uq_s":324,"uq_sl":324,"dup_s":0,"dup_sl":0,"dur_total":1923.588,"dur_mean":5.937,"dur_median":5.94,"dur_freq":"0-1-33-41-38-55-46-45-42-21-2","v_mean":64.8,"v_median":6.0,"v_freq":"2-0-1-0-0-0-1-1-0-0-0-0-0-0-0-0-0","s_mean":1.0,"s_median":1.0,"s_freq":"0-324-0-0-0-0-0-0-0-0-0-0-0-0-0-0","dem_table":"0-0-0-0-0|1-0-0-0-1|66-0-0-0-66|0-0-0-0-0|0-0-0-0-0|115-0-0-0-115|0-0-0-0-0|0-0-0-0-0|0-0-0-0-0|0-0-0-142-142|182-0-0-142-324"},{"ver":"9.0","lc":"myv","alg":"s1","sp":"train","clips":522,"uq_v":1,"uq_s":522,"uq_sl":522,"dup_s":0,"dup_sl":0,"dur_total":2865.564,"dur_mean":5.4895862069,"dur_median":5.328,"dur_freq":"0-1-76-76-81-84-74-59-40-27-4","v_mean":522.0,"v_median":522.0,"v_freq":"0-0-0-0-0-0-0-0-0-1-0-0-0-0-0-0-0","s_mean":1.0,"s_median":1.0,"s_freq":"0-522-0-0-0-0-0-0-0-0-0-0-0-0-0-0","dem_table":"0-0-0-0-0|0-0-0-0-0|354-0-0-0-354|0-0-0-0-0|0-0-0-0-0|0-0-0-0-0|0-0-0-0-0|0-0-0-0-0|0-0-0-0-0|0-0-0-168-168|354-0-0-168-522"},{"ver":"9.0","lc":"myv","alg":"s1","sp":"dev","clips":351,"uq_v":1,"uq_s":351,"uq_sl":351,"dup_s":0,"dup_sl":0,"dur_total":2086.056,"dur_mean":5.9431794872,"dur_median":5.94,"dur_freq":"0-2-32-35-49-65-55-56-31-21-5","v_mean":351.0,"v_median":351.0,"v_freq":"0-0-0-0-0-0-0-0-1-0-0-0-0-0-0-0-0","s_mean":1.0,"s_median":1.0,"s_freq":"0-351-0-0-0-0-0-0-0-0-0-0-0-0-0-0","dem_table":"0-0-0-0-0|0-0-0-0-0|0-0-0-0-0|0-0-0-0-0|0-0-0-0-0|338-0-0-0-338|0-0-0-0-0|0-0-0-0-0|0-0-0-0-0|0-0-0-13-13|338-0-0-13-351"},{"ver":"9.0","lc":"myv","alg":"s1","sp":"test","clips":297,"uq_v":3,"uq_s":297,"uq_sl":297,"dup_s":0,"dup_sl":0,"dur_total":1672.02,"dur_mean":5.6296969697,"dur_median":5.436,"dur_freq":"0-0-23-47-53-59-42-32-26-12-3","v_mean":99.0,"v_median":58.0,"v_freq":"0-0-0-0-0-2-0-1-0-0-0-0-0-0-0-0-0","s_mean":1.0,"s_median":1.0,"s_freq":"0-297-0-0-0-0-0-0-0-0-0-0-0-0-0-0","dem_table":"0-0-0-0-0|48-0-0-0-48|59-0-0-0-59|0-0-0-0-0|0-0-0-0-0|0-0-0-0-0|0-0-0-0-0|0-0-0-0-0|0-0-0-0-0|0-0-0-190-190|107-0-0-190-297"},{"ver":"9.0","lc":"myv","alg":"s99","sp":"train","clips":525,"uq_v":1,"uq_s":525,"uq_sl":525,"dup_s":0,"dup_sl":0,"dur_total":2875.068,"dur_mean":5.47632,"dur_median":5.328,"dur_freq":"0-1-77-78-81-84-74-59-40-27-4","v_mean":525.0,"v_median":525.0,"v_freq":"0-0-0-0-0-0-0-0-0-1-0-0-0-0-0-0-0","s_mean":1.0,"s_median":1.0,"s_freq":"0-525-0-0-0-0-0-0-0-0-0-0-0-0-0-0","dem_table":"0-0-0-0-0|0-0-0-0-0|357-0-0-0-357|0-0-0-0-0|0-0-0-0-0|0-0-0-0-0|0-0-0-0-0|0-0-0-0-0|0-0-0-0-0|0-0-0-168-168|357-0-0-168-525"},{"ver":"9.0","lc":"myv","alg":"s99","sp":"dev","clips":351,"uq_v":1,"uq_s":351,"uq_sl":351,"dup_s":0,"dup_sl":0,"dur_total":2086.056,"dur_mean":5.9431794872,"dur_median":5.94,"dur_freq":"0-2-32-35-49-65-55-56-31-21-5","v_mean":351.0,"v_median":351.0,"v_freq":"0-0-0-0-0-0-0-0-1-0-0-0-0-0-0-0-0","s_mean":1.0,"s_median":1.0,"s_freq":"0-351-0-0-0-0-0-0-0-0-0-0-0-0-0-0","dem_table":"0-0-0-0-0|0-0-0-0-0|0-0-0-0-0|0-0-0-0-0|0-0-0-0-0|338-0-0-0-338|0-0-0-0-0|0-0-0-0-0|0-0-0-0-0|0-0-0-13-13|338-0-0-13-351"},{"ver":"9.0","lc":"myv","alg":"s99","sp":"test","clips":297,"uq_v":3,"uq_s":297,"uq_sl":297,"dup_s":0,"dup_sl":0,"dur_total":1672.02,"dur_mean":5.6296969697,"dur_median":5.436,"dur_freq":"0-0-23-47-53-59-42-32-26-12-3","v_mean":99.0,"v_median":58.0,"v_freq":"0-0-0-0-0-2-0-1-0-0-0-0-0-0-0-0-0","s_mean":1.0,"s_median":1.0,"s_freq":"0-297-0-0-0-0-0-0-0-0-0-0-0-0-0-0","dem_table":"0-0-0-0-0|48-0-0-0-48|59-0-0-0-59|0-0-0-0-0|0-0-0-0-0|0-0-0-0-0|0-0-0-0-0|0-0-0-0-0|0-0-0-0-0|0-0-0-190-190|107-0-0-190-297"},{"ver":"9.0","lc":"myv","alg":"v1","sp":"train","clips":939,"uq_v":3,"uq_s":938,"uq_sl":938,"dup_s":1,"dup_sl":1,"dur_total":5330.196,"dur_mean":5.6764600639,"dur_median":5.58,"dur_freq":"0-3-114-122-137-162-140-123-78-50-10","v_mean":313.0,"v_median":351.0,"v_freq":"0-0-0-0-0-1-0-0-1-1-0-0-0-0-0-0-0","s_mean":1.0010660981,"s_median":1.0,"s_freq":"0-937-1-0-0-0-0-0-0-0-0-0-0-0-0-0","dem_table":"0-0-0-0-0|0-0-0-0-0|357-0-0-0-357|0-0-0-0-0|0-0-0-0-0|338-0-0-0-338|0-0-0-0-0|0-0-0-0-0|0-0-0-0-0|0-0-0-244-244|695-0-0-244-939"},{"ver":"9.0","lc":"myv","alg":"v1","sp":"dev","clips":116,"uq_v":1,"uq_s":116,"uq_sl":116,"dup_s":0,"dup_sl":0,"dur_total":642.96,"dur_mean":5.5427586207,"dur_median":5.238,"dur_freq":"0-0-5-22-25-23-17-10-8-5-1","v_mean":116.0,"v_median":116.0,"v_freq":"0-0-0-0-0-0-1-0-0-0-0-0-0-0-0-0-0","s_mean":1.0,"s_median":1.0,"s_freq":"0-116-0-0-0-0-0-0-0-0-0-0-0-0-0-0","dem_table":"0-0-0-0-0|0-0-0-0-0|40-0-0-0-40|0-0-0-0-0|0-0-0-0-0|0-0-0-0-0|0-0-0-0-0|0-0-0-0-0|0-0-0-0-0|0-0-0-76-76|40-0-0-76-116"},{"ver":"9.0","lc":"myv","alg":"v1","sp":"test","clips":117,"uq_v":3,"uq_s":117,"uq_sl":117,"dup_s":0,"dup_sl":0,"dur_total":657.252,"dur_mean":5.6175384615,"dur_median":5.58,"dur_freq":"0-0-12-16-21-23-14-14-11-5-1","v_mean":39.0,"v_median":41.0,"v_freq":"0-0-0-0-1-2-0-0-0-0-0-0-0-0-0-0-0","s_mean":1.0,"s_median":1.0,"s_freq":"0-117-0-0-0-0-0-0-0-0-0-0-0-0-0-0","dem_table":"0-0-0-0-0|48-0-0-0-48|18-0-0-0-18|0-0-0-0-0|0-0-0-0-0|0-0-0-0-0|0-0-0-0-0|0-0-0-0-0|0-0-0-0-0|0-0-0-51-51|66-0-0-51-117"}]}