{"schema":{"fields":[{"name":"ver","type":"string"},{"name":"lc","type":"string"},{"name":"alg","type":"string"},{"name":"sp","type":"string"},{"name":"clips","type":"integer"},{"name":"uq_v","type":"integer"},{"name":"uq_s","type":"integer"},{"name":"uq_sl","type":"integer"},{"name":"dup_s","type":"integer"},{"name":"dup_sl","type":"integer"},{"name":"dur_total","type":"number"},{"name":"dur_mean","type":"number"},{"name":"dur_median","type":"number"},{"name":"dur_freq","type":"string"},{"name":"v_mean","type":"number"},{"name":"v_median","type":"number"},{"name":"v_freq","type":"string"},{"name":"s_mean","type":"number"},{"name":"s_median","type":"number"},{"name":"s_freq","type":"string"},{"name":"dem_table","type":"string"}],"pandas_version":"1.4.0"},"data":[{"ver":"11.0","lc":"mr","alg":"","sp":"clips","clips":15860,"uq_v":78,"uq_s":6543,"uq_sl":6543,"dup_s":9317,"dup_sl":9317,"dur_total":98196.084,"dur_mean":6.1914302648,"dur_median":6.048,"dur_freq":"0-34-303-1603-2751-3158-2707-2350-1595-1082-277","v_mean":203.3333333333,"v_median":101.5,"v_freq":"3-1-9-7-3-11-16-10-9-6-3-0-0-0-0-0-0","s_mean":2.4239645423,"s_median":3.0,"s_freq":"0-512-2751-3274-6-0-0-0-0-0-0-0-0-0-0-0","dem_table":"519-7948-0-0-8467|449-4090-0-0-4539|2045-0-0-0-2045|0-0-0-0-0|0-0-0-0-0|0-64-0-0-64|0-0-0-0-0|0-0-0-0-0|0-0-0-0-0|0-0-0-745-745|3013-12102-0-745-15860"},{"ver":"11.0","lc":"mr","alg":"","sp":"validated","clips":10804,"uq_v":72,"uq_s":5743,"uq_sl":5743,"dup_s":5061,"dup_sl":5061,"dur_total":65322.864,"dur_mean":6.0461740096,"dur_median":5.832,"dur_freq":"0-3-223-1225-2025-2285-1779-1514-958-643-149","v_mean":150.0555555556,"v_median":47.5,"v_freq":"3-2-11-4-7-15-10-8-5-5-2-0-0-0-0-0-0","s_mean":1.8812467352,"s_median":2.0,"s_freq":"0-1186-4054-502-1-0-0-0-0-0-0-0-0-0-0-0","dem_table":"301-5774-0-0-6075|280-2879-0-0-3159|1078-0-0-0-1078|0-0-0-0-0|0-0-0-0-0|0-36-0-0-36|0-0-0-0-0|0-0-0-0-0|0-0-0-0-0|0-0-0-456-456|1659-8689-0-456-10804"},{"ver":"11.0","lc":"mr","alg":"","sp":"invalidated","clips":2237,"uq_v":72,"uq_s":1870,"uq_sl":1870,"dup_s":367,"dup_sl":367,"dur_total":14861.376,"dur_mean":6.6434403219,"dur_median":6.66,"dur_freq":"0-27-39-129-266-359-446-398-294-214-65","v_mean":31.0694444444,"v_median":8.0,"v_freq":"10-9-16-11-16-2-4-3-0-1-0-0-0-0-0-0-0","s_mean":1.1962566845,"s_median":1.0,"s_freq":"0-1587-199-84-0-0-0-0-0-0-0-0-0-0-0-0","dem_table":"51-656-0-0-707|37-353-0-0-390|933-0-0-0-933|0-0-0-0-0|0-0-0-0-0|0-28-0-0-28|0-0-0-0-0|0-0-0-0-0|0-0-0-0-0|0-0-0-179-179|1021-1037-0-179-2237"},{"ver":"11.0","lc":"mr","alg":"","sp":"other","clips":2819,"uq_v":51,"uq_s":2773,"uq_sl":2773,"dup_s":46,"dup_sl":46,"dur_total":18011.844,"dur_mean":6.3894444839,"dur_median":6.3,"dur_freq":"0-4-41-249-460-514-482-438-343-225-63","v_mean":55.2745098039,"v_median":23.0,"v_freq":"6-4-5-3-12-9-6-3-3-0-0-0-0-0-0-0-0","s_mean":1.0165885323,"s_median":1.0,"s_freq":"0-2731-38-4-0-0-0-0-0-0-0-0-0-0-0-0","dem_table":"167-1518-0-0-1685|132-858-0-0-990|34-0-0-0-34|0-0-0-0-0|0-0-0-0-0|0-0-0-0-0|0-0-0-0-0|0-0-0-0-0|0-0-0-0-0|0-0-0-110-110|333-2376-0-110-2819"},{"ver":"11.0","lc":"mr","alg":"s1","sp":"train","clips":2245,"uq_v":9,"uq_s":2245,"uq_sl":2245,"dup_s":0,"dup_sl":0,"dur_total":13412.088,"dur_mean":5.9742040089,"dur_median":5.76,"dur_freq":"0-1-50-265-411-507-364-314-189-113-31","v_mean":249.4444444444,"v_median":259.0,"v_freq":"0-0-0-0-0-0-0-3-6-0-0-0-0-0-0-0-0","s_mean":1.0,"s_median":1.0,"s_freq":"0-2245-0-0-0-0-0-0-0-0-0-0-0-0-0-0","dem_table":"0-1271-0-0-1271|82-491-0-0-573|383-0-0-0-383|0-0-0-0-0|0-0-0-0-0|0-0-0-0-0|0-0-0-0-0|0-0-0-0-0|0-0-0-0-0|0-0-0-18-18|465-1762-0-18-2245"},{"ver":"11.0","lc":"mr","alg":"s1","sp":"dev","clips":1682,"uq_v":10,"uq_s":1682,"uq_sl":1682,"dup_s":0,"dup_sl":0,"dur_total":10686.996,"dur_mean":6.3537431629,"dur_median":6.228,"dur_freq":"0-0-18-153-276-335-299-261-168-132-40","v_mean":168.2,"v_median":168.0,"v_freq":"0-0-0-0-0-0-3-6-1-0-0-0-0-0-0-0-0","s_mean":1.0,"s_median":1.0,"s_freq":"0-1682-0-0-0-0-0-0-0-0-0-0-0-0-0-0","dem_table":"0-1071-0-0-1071|0-327-0-0-327|111-0-0-0-111|0-0-0-0-0|0-0-0-0-0|0-0-0-0-0|0-0-0-0-0|0-0-0-0-0|0-0-0-0-0|0-0-0-173-173|111-1398-0-173-1682"},{"ver":"11.0","lc":"mr","alg":"s1","sp":"test","clips":1816,"uq_v":53,"uq_s":1816,"uq_sl":1816,"dup_s":0,"dup_sl":0,"dur_total":11369.124,"dur_mean":6.260530837,"dur_median":6.066,"dur_freq":"0-1-26-161-324-370-330-241-192-139-32","v_mean":34.2641509434,"v_median":31.0,"v_freq":"3-2-11-4-7-17-9-0-0-0-0-0-0-0-0-0-0","s_mean":1.0,"s_median":1.0,"s_freq":"0-1816-0-0-0-0-0-0-0-0-0-0-0-0-0-0","dem_table":"278-894-0-0-1172|20-370-0-0-390|59-0-0-0-59|0-0-0-0-0|0-0-0-0-0|0-29-0-0-29|0-0-0-0-0|0-0-0-0-0|0-0-0-0-0|0-0-0-166-166|357-1293-0-166-1816"},{"ver":"11.0","lc":"mr","alg":"s99","sp":"train","clips":4440,"uq_v":5,"uq_s":3600,"uq_sl":3600,"dup_s":840,"dup_sl":840,"dur_total":26433.864,"dur_mean":5.953572973,"dur_median":5.76,"dur_freq":"0-1-82-525-869-993-695-644-374-219-38","v_mean":888.0,"v_median":745.0,"v_freq":"0-0-0-0-0-0-0-0-0-3-2-0-0-0-0-0-0","s_mean":1.2333333333,"s_median":1.0,"s_freq":"0-2767-826-7-0-0-0-0-0-0-0-0-0-0-0-0","dem_table":"0-1828-0-0-1828|260-1981-0-0-2241|324-0-0-0-324|0-0-0-0-0|0-0-0-0-0|0-0-0-0-0|0-0-0-0-0|0-0-0-0-0|0-0-0-0-0|0-0-0-47-47|584-3809-0-47-4440"},{"ver":"11.0","lc":"mr","alg":"s99","sp":"dev","clips":3255,"uq_v":8,"uq_s":2773,"uq_sl":2773,"dup_s":482,"dup_sl":482,"dur_total":19105.164,"dur_mean":5.8694820276,"dur_median":5.688,"dur_freq":"0-1-99-430-643-676-535-425-244-159-43","v_mean":406.875,"v_median":401.5,"v_freq":"0-0-0-0-0-0-0-1-5-2-0-0-0-0-0-0-0","s_mean":1.1738189686,"s_median":1.0,"s_freq":"0-2315-434-24-0-0-0-0-0-0-0-0-0-0-0-0","dem_table":"0-2466-0-0-2466|0-249-0-0-249|536-0-0-0-536|0-0-0-0-0|0-0-0-0-0|0-0-0-0-0|0-0-0-0-0|0-0-0-0-0|0-0-0-0-0|0-0-0-4-4|536-2715-0-4-3255"},{"ver":"11.0","lc":"mr","alg":"s99","sp":"test","clips":3109,"uq_v":59,"uq_s":2641,"uq_sl":2641,"dup_s":468,"dup_sl":468,"dur_total":19783.836,"dur_mean":6.3634081698,"dur_median":6.228,"dur_freq":"0-1-42-270-513-616-549-445-340-265-68","v_mean":52.6949152542,"v_median":43.0,"v_freq":"3-2-11-4-7-15-10-7-0-0-0-0-0-0-0-0-0","s_mean":1.1772056039,"s_median":1.0,"s_freq":"0-2195-424-22-0-0-0-0-0-0-0-0-0-0-0-0","dem_table":"301-1480-0-0-1781|20-649-0-0-669|218-0-0-0-218|0-0-0-0-0|0-0-0-0-0|0-36-0-0-36|0-0-0-0-0|0-0-0-0-0|0-0-0-0-0|0-0-0-405-405|539-2165-0-405-3109"},{"ver":"11.0","lc":"mr","alg":"v1","sp":"train","clips":8666,"uq_v":22,"uq_s":5429,"uq_sl":5429,"dup_s":3237,"dup_sl":3237,"dur_total":52073.316,"dur_mean":6.0089217632,"dur_median":5.796,"dur_freq":"0-2-193-1020-1641-1830-1399-1239-728-503-111","v_mean":393.9090909091,"v_median":296.5,"v_freq":"0-0-0-0-0-5-1-4-5-5-2-0-0-0-0-0-0","s_mean":1.5962424019,"s_median":2.0,"s_freq":"0-2341-2939-149-0-0-0-0-0-0-0-0-0-0-0-0","dem_table":"47-4733-0-0-4780|260-2450-0-0-2710|905-0-0-0-905|0-0-0-0-0|0-0-0-0-0|0-0-0-0-0|0-0-0-0-0|0-0-0-0-0|0-0-0-0-0|0-0-0-271-271|1212-7183-0-271-8666"},{"ver":"11.0","lc":"mr","alg":"v1","sp":"dev","clips":1063,"uq_v":14,"uq_s":1008,"uq_sl":1008,"dup_s":55,"dup_sl":55,"dur_total":6599.592,"dur_mean":6.2084590781,"dur_median":6.048,"dur_freq":"0-1-14-95-196-214-198-147-112-70-16","v_mean":75.9285714286,"v_median":72.0,"v_freq":"0-0-0-0-0-6-7-1-0-0-0-0-0-0-0-0-0","s_mean":1.0545634921,"s_median":1.0,"s_freq":"0-953-55-0-0-0-0-0-0-0-0-0-0-0-0-0","dem_table":"144-346-0-0-490|0-271-0-0-271|155-0-0-0-155|0-0-0-0-0|0-0-0-0-0|0-36-0-0-36|0-0-0-0-0|0-0-0-0-0|0-0-0-0-0|0-0-0-111-111|299-653-0-111-1063"},{"ver":"11.0","lc":"mr","alg":"v1","sp":"test","clips":1075,"uq_v":36,"uq_s":1023,"uq_sl":1023,"dup_s":52,"dup_sl":52,"dur_total":6649.956,"dur_mean":6.1860055814,"dur_median":5.94,"dur_freq":"0-0-16-110-188-241-182-128-118-70-22","v_mean":29.8611111111,"v_median":12.5,"v_freq":"3-2-11-4-7-4-2-3-0-0-0-0-0-0-0-0-0","s_mean":1.0508308895,"s_median":1.0,"s_freq":"0-971-52-0-0-0-0-0-0-0-0-0-0-0-0-0","dem_table":"110-695-0-0-805|20-158-0-0-178|18-0-0-0-18|0-0-0-0-0|0-0-0-0-0|0-0-0-0-0|0-0-0-0-0|0-0-0-0-0|0-0-0-0-0|0-0-0-74-74|148-853-0-74-1075"}]}