{"schema":{"fields":[{"name":"ver","type":"string"},{"name":"lc","type":"string"},{"name":"alg","type":"string"},{"name":"sp","type":"string"},{"name":"clips","type":"integer"},{"name":"uq_v","type":"integer"},{"name":"uq_s","type":"integer"},{"name":"uq_sl","type":"integer"},{"name":"dur_total","type":"number"},{"name":"dur_avg","type":"number"},{"name":"dur_med","type":"number"},{"name":"dur_std","type":"number"},{"name":"dur_freq","type":"string"},{"name":"v_avg","type":"number"},{"name":"v_med","type":"number"},{"name":"v_std","type":"number"},{"name":"v_freq","type":"string"},{"name":"s_avg","type":"number"},{"name":"s_med","type":"number"},{"name":"s_std","type":"number"},{"name":"s_freq","type":"string"},{"name":"uv_sum","type":"integer"},{"name":"uv_avg","type":"number"},{"name":"uv_med","type":"number"},{"name":"uv_std","type":"number"},{"name":"uv_freq","type":"string"},{"name":"dv_sum","type":"integer"},{"name":"dv_avg","type":"number"},{"name":"dv_med","type":"number"},{"name":"dv_std","type":"number"},{"name":"dv_freq","type":"string"},{"name":"dem_table","type":"string"},{"name":"dem_uq","type":"string"},{"name":"dem_fix_r","type":"string"},{"name":"dem_fix_v","type":"string"}],"pandas_version":"1.4.0"},"data":[{"ver":"4","lc":"eo","alg":"","sp":"clips","clips":29326,"uq_v":215,"uq_s":10558,"uq_sl":10558,"dur_total":147804.168,"dur_avg":5.042,"dur_med":4.776,"dur_std":1.739,"dur_freq":"0#305#2552#6148#7238#5272#3595#2203#1209#595#200#0#0","v_avg":136.4,"v_med":19.0,"v_std":614.766,"v_freq":"0#3#6#64#34#27#27#23#12#8#7#2#0#2#0#0#0#0","s_avg":2.778,"s_med":3.0,"s_std":1.177,"s_freq":"0#2358#1537#2851#3752#38#13#7#2#0#0#0#0#0#0#0","uv_sum":53766,"uv_avg":2.0,"uv_med":2.0,"uv_std":1.414,"uv_freq":"922#3256#24938#206#4#0#0#0#0#0#0#0#0#0#0","dv_sum":4601,"dv_avg":2.0,"dv_med":2.0,"dv_std":1.414,"dv_freq":"25913#2231#1177#4#1#0#0#0#0#0#0#0#0#0#0","dem_table":"493#0#10#0#503|8753#934#160#3615#13462|1519#285#15#0#1819|8544#689#0#0#9233|805#219#0#0#1024|192#0#0#0#192|109#0#0#0#109|0#0#0#0#0|0#0#0#0#0|0#0#0#2984#2984|20415#2127#185#6599#29326","dem_uq":"9#0#1#0#10|35#7#4#2#48|24#6#1#0#31|12#3#0#0#15|7#5#0#0#12|3#0#0#0#3|3#0#0#0#3|0#0#0#0#0|0#0#0#0#0|0#0#0#93#93|93#21#6#95#215","dem_fix_r":"","dem_fix_v":""},{"ver":"4","lc":"eo","alg":"","sp":"validated","clips":25147,"uq_v":211,"uq_s":9840,"uq_sl":9840,"dur_total":124717.704,"dur_avg":4.96,"dur_med":4.704,"dur_std":1.688,"dur_freq":"0#281#2277#5467#6273#4592#3032#1780#903#412#130#0#0","v_avg":119.18,"v_med":15.0,"v_std":504.058,"v_freq":"0#5#14#58#31#28#23#25#11#9#3#2#0#2#0#0#0#0","s_avg":2.556,"s_med":3.0,"s_std":1.026,"s_freq":"0#2012#2209#3818#1765#21#8#6#1#0#0#0#0#0#0#0","uv_sum":50508,"uv_avg":3.0,"uv_med":3.0,"uv_std":0.816,"uv_freq":"0#0#24937#206#4#0#0#0#0#0#0#0#0#0#0","dv_sum":1833,"dv_avg":1.0,"dv_med":1.0,"dv_std":0.816,"dv_freq":"23319#1823#5#0#0#0#0#0#0#0#0#0#0#0#0","dem_table":"422#0#10#0#432|8205#896#133#3554#12788|1413#277#14#0#1704|6221#668#0#0#6889|346#183#0#0#529|190#0#0#0#190|108#0#0#0#108|0#0#0#0#0|0#0#0#0#0|0#0#0#2507#2507|16905#2024#157#6061#25147","dem_uq":"9#0#1#0#10|34#7#4#2#47|24#5#1#0#30|12#3#0#0#15|7#5#0#0#12|3#0#0#0#3|3#0#0#0#3|0#0#0#0#0|0#0#0#0#0|0#0#0#91#91|92#20#6#93#211","dem_fix_r":"","dem_fix_v":""},{"ver":"4","lc":"eo","alg":"","sp":"invalidated","clips":1527,"uq_v":145,"uq_s":1434,"uq_sl":1434,"dur_total":8786.784,"dur_avg":5.762,"dur_med":5.544,"dur_std":2.026,"dur_freq":"0#17#96#216#282#259#234#172#141#74#34#0#0","v_avg":10.531,"v_med":3.0,"v_std":31.245,"v_freq":"0#50#30#27#14#17#4#1#1#1#0#0#0#0#0#0#0#0","s_avg":1.065,"s_med":1.0,"s_std":0.263,"s_freq":"0#1346#84#3#1#0#0#0#0#0#0#0#0#0#0#0","uv_sum":857,"uv_avg":1.0,"uv_med":1.0,"uv_std":0.816,"uv_freq":"671#855#1#0#0#0#0#0#0#0#0#0#0#0#0","dv_sum":2710,"dv_avg":2.5,"dv_med":2.5,"dv_std":1.118,"dv_freq":"0#350#1172#4#1#0#0#0#0#0#0#0#0#0#0","dem_table":"70#0#0#0#70|345#29#25#58#457|84#8#1#0#93|372#20#0#0#392|15#35#0#0#50|2#0#0#0#2|1#0#0#0#1|0#0#0#0#0|0#0#0#0#0|0#0#0#462#462|889#92#26#520#1527","dem_uq":"7#0#0#0#7|28#5#3#2#38|17#4#1#0#22|9#3#0#0#12|5#4#0#0#9|2#0#0#0#2|1#0#0#0#1|0#0#0#0#0|0#0#0#0#0|0#0#0#54#54|69#16#4#56#145","dem_fix_r":"","dem_fix_v":""},{"ver":"4","lc":"eo","alg":"","sp":"other","clips":2652,"uq_v":28,"uq_s":2602,"uq_sl":2602,"dur_total":14299.68,"dur_avg":5.406,"dur_med":4.992,"dur_std":1.893,"dur_freq":"0#7#179#465#683#421#329#251#165#109#36#0#0","v_avg":94.714,"v_med":2.0,"v_std":366.272,"v_freq":"0#11#7#4#2#0#1#0#1#1#0#1#0#0#0#0#0#0","s_avg":1.019,"s_med":1.0,"s_std":0.143,"s_freq":"0#2554#46#2#0#0#0#0#0#0#0#0#0#0#0#0","uv_sum":2401,"uv_avg":0.5,"uv_med":0.5,"uv_std":0.5,"uv_freq":"251#2401#0#0#0#0#0#0#0#0#0#0#0#0#0","dv_sum":58,"dv_avg":0.5,"dv_med":0.5,"dv_std":0.5,"dv_freq":"2594#58#0#0#0#0#0#0#0#0#0#0#0#0#0","dem_table":"1#0#0#0#1|203#9#2#3#217|22#0#0#0#22|1951#1#0#0#1952|444#1#0#0#445|0#0#0#0#0|0#0#0#0#0|0#0#0#0#0|0#0#0#0#0|0#0#0#15#15|2621#11#2#18#2652","dem_uq":"1#0#0#0#1|6#1#1#1#9|5#0#0#0#5|2#1#0#0#3|1#1#0#0#2|0#0#0#0#0|0#0#0#0#0|0#0#0#0#0|0#0#0#0#0|0#0#0#8#8|15#3#1#9#28","dem_fix_r":"","dem_fix_v":""},{"ver":"4","lc":"eo","alg":"s1","sp":"train","clips":3845,"uq_v":10,"uq_s":3845,"uq_sl":3845,"dur_total":20006.568,"dur_avg":5.203,"dur_med":4.92,"dur_std":1.885,"dur_freq":"0#49#371#759#800#650#493#364#222#106#31#0#0","v_avg":384.5,"v_med":329.0,"v_std":217.175,"v_freq":"0#0#0#0#0#0#0#0#4#4#2#0#0#0#0#0#0#0","s_avg":1.0,"s_med":1.0,"s_std":0.0,"s_freq":"0#3845#0#0#0#0#0#0#0#0#0#0#0#0#0#0","uv_sum":7717,"uv_avg":2.5,"uv_med":2.5,"uv_std":0.5,"uv_freq":"0#0#3818#27#0#0#0#0#0#0#0#0#0#0#0","dv_sum":211,"dv_avg":0.5,"dv_med":0.5,"dv_std":0.5,"dv_freq":"3634#211#0#0#0#0#0#0#0#0#0#0#0#0#0","dem_table":"0#0#0#0#0|918#178#0#567#1663|439#0#0#0#439|1399#344#0#0#1743|0#0#0#0#0|0#0#0#0#0|0#0#0#0#0|0#0#0#0#0|0#0#0#0#0|0#0#0#0#0|2756#522#0#567#3845","dem_uq":"0#0#0#0#0|3#1#0#2#6|1#0#0#0#1|2#1#0#0#3|0#0#0#0#0|0#0#0#0#0|0#0#0#0#0|0#0#0#0#0|0#0#0#0#0|0#0#0#0#0|6#2#0#2#10","dem_fix_r":"","dem_fix_v":""},{"ver":"4","lc":"eo","alg":"s1","sp":"dev","clips":2965,"uq_v":26,"uq_s":2965,"uq_sl":2965,"dur_total":15111.648,"dur_avg":5.097,"dur_med":4.776,"dur_std":1.858,"dur_freq":"0#20#293#656#667#494#342#235#137#84#37#0#0","v_avg":114.038,"v_med":100.0,"v_std":54.895,"v_freq":"0#0#0#0#0#1#2#15#8#0#0#0#0#0#0#0#0#0","s_avg":1.0,"s_med":1.0,"s_std":0.0,"s_freq":"0#2965#0#0#0#0#0#0#0#0#0#0#0#0#0#0","uv_sum":5943,"uv_avg":2.5,"uv_med":2.5,"uv_std":0.5,"uv_freq":"0#0#2952#13#0#0#0#0#0#0#0#0#0#0#0","dv_sum":221,"dv_avg":0.5,"dv_med":0.5,"dv_std":0.5,"dv_freq":"2744#221#0#0#0#0#0#0#0#0#0#0#0#0#0","dem_table":"118#0#0#0#118|847#140#0#0#987|159#93#0#0#252|294#204#0#0#498|224#0#0#0#224|78#0#0#0#78|0#0#0#0#0|0#0#0#0#0|0#0#0#0#0|0#0#0#808#808|1720#437#0#808#2965","dem_uq":"1#0#0#0#1|10#1#0#0#11|2#1#0#0#3|2#2#0#0#4|1#0#0#0#1|1#0#0#0#1|0#0#0#0#0|0#0#0#0#0|0#0#0#0#0|0#0#0#5#5|17#4#0#5#26","dem_fix_r":"","dem_fix_v":""},{"ver":"4","lc":"eo","alg":"s1","sp":"test","clips":3030,"uq_v":175,"uq_s":3030,"uq_sl":3030,"dur_total":16324.776,"dur_avg":5.388,"dur_med":5.16,"dur_std":1.671,"dur_freq":"0#2#128#530#741#629#470#277#161#77#15#0#0","v_avg":17.314,"v_med":9.0,"v_std":18.253,"v_freq":"0#5#14#59#31#40#17#9#0#0#0#0#0#0#0#0#0#0","s_avg":1.0,"s_med":1.0,"s_std":0.0,"s_freq":"0#3030#0#0#0#0#0#0#0#0#0#0#0#0#0#0","uv_sum":6092,"uv_avg":3.0,"uv_med":3.0,"uv_std":0.816,"uv_freq":"0#0#2999#30#1#0#0#0#0#0#0#0#0#0#0","dv_sum":256,"dv_avg":1.0,"dv_med":1.0,"dv_std":0.816,"dv_freq":"2775#254#1#0#0#0#0#0#0#0#0#0#0#0#0","dem_table":"184#0#10#0#194|433#72#110#0#615|442#111#13#0#566|125#0#0#0#125|118#159#0#0#277|62#0#0#0#62|88#0#0#0#88|0#0#0#0#0|0#0#0#0#0|0#0#0#1103#1103|1452#342#133#1103#3030","dem_uq":"8#0#1#0#9|21#5#4#0#30|21#4#1#0#26|8#0#0#0#8|6#5#0#0#11|2#0#0#0#2|3#0#0#0#3|0#0#0#0#0|0#0#0#0#0|0#0#0#86#86|69#14#6#86#175","dem_fix_r":"","dem_fix_v":""},{"ver":"4","lc":"eo","alg":"s99","sp":"train","clips":13263,"uq_v":4,"uq_s":8232,"uq_sl":8232,"dur_total":64303.296,"dur_avg":4.848,"dur_med":4.632,"dur_std":1.677,"dur_freq":"0#212#1379#2929#3373#2334#1508#859#412#188#69#0#0","v_avg":3315.75,"v_med":3321.5,"v_std":1539.863,"v_freq":"0#0#0#0#0#0#0#0#0#0#0#2#0#2#0#0#0#0","s_avg":1.611,"s_med":2.0,"s_std":0.675,"s_freq":"0#4096#3242#893#1#0#0#0#0#0#0#0#0#0#0#0","uv_sum":26624,"uv_avg":3.0,"uv_med":3.0,"uv_std":0.816,"uv_freq":"0#0#13166#96#1#0#0#0#0#0#0#0#0#0#0","dv_sum":867,"dv_avg":1.0,"dv_med":1.0,"dv_std":0.816,"dv_freq":"12398#863#2#0#0#0#0#0#0#0#0#0#0#0#0","dem_table":"0#0#0#0#0|4802#0#0#3554#8356|0#0#0#0#0|4907#0#0#0#4907|0#0#0#0#0|0#0#0#0#0|0#0#0#0#0|0#0#0#0#0|0#0#0#0#0|0#0#0#0#0|9709#0#0#3554#13263","dem_uq":"0#0#0#0#0|1#0#0#2#3|0#0#0#0#0|1#0#0#0#1|0#0#0#0#0|0#0#0#0#0|0#0#0#0#0|0#0#0#0#0|0#0#0#0#0|0#0#0#0#0|2#0#0#2#4","dem_fix_r":"","dem_fix_v":""},{"ver":"4","lc":"eo","alg":"s99","sp":"dev","clips":5116,"uq_v":12,"uq_s":4393,"uq_sl":4393,"dur_total":25169.52,"dur_avg":4.92,"dur_med":4.656,"dur_std":1.662,"dur_freq":"0#39#498#1190#1198#945#599#369#201#64#13#0#0","v_avg":426.333,"v_med":364.5,"v_std":148.836,"v_freq":"0#0#0#0#0#0#0#0#0#9#3#0#0#0#0#0#0#0","s_avg":1.165,"s_med":1.0,"s_std":0.398,"s_freq":"0#3715#634#43#1#0#0#0#0#0#0#0#0#0#0#0","uv_sum":10290,"uv_avg":3.0,"uv_med":3.0,"uv_std":0.816,"uv_freq":"0#0#5060#54#2#0#0#0#0#0#0#0#0#0#0","dv_sum":392,"dv_avg":0.5,"dv_med":0.5,"dv_std":0.5,"dv_freq":"4724#392#0#0#0#0#0#0#0#0#0#0#0#0#0","dem_table":"0#0#0#0#0|1640#815#0#0#2455|640#0#0#0#640|727#404#0#0#1131|0#0#0#0#0|0#0#0#0#0|0#0#0#0#0|0#0#0#0#0|0#0#0#0#0|0#0#0#890#890|3007#1219#0#890#5116","dem_uq":"0#0#0#0#0|4#2#0#0#6|1#0#0#0#1|1#1#0#0#2|0#0#0#0#0|0#0#0#0#0|0#0#0#0#0|0#0#0#0#0|0#0#0#0#0|0#0#0#3#3|6#3#0#3#12","dem_fix_r":"","dem_fix_v":""},{"ver":"4","lc":"eo","alg":"s99","sp":"test","clips":6768,"uq_v":195,"uq_s":5080,"uq_sl":5080,"dur_total":35244.888,"dur_avg":5.208,"dur_med":4.944,"dur_std":1.701,"dur_freq":"0#30#400#1348#1702#1313#925#552#290#160#48#0#0","v_avg":34.708,"v_med":12.0,"v_std":48.746,"v_freq":"0#5#14#58#31#28#23#25#11#0#0#0#0#0#0#0#0#0","s_avg":1.332,"s_med":1.0,"s_std":0.66,"s_freq":"0#3776#1027#206#48#13#7#3#0#0#0#0#0#0#0#0","uv_sum":13594,"uv_avg":3.0,"uv_med":3.0,"uv_std":0.816,"uv_freq":"0#0#6711#56#1#0#0#0#0#0#0#0#0#0#0","dv_sum":574,"dv_avg":1.0,"dv_med":1.0,"dv_std":0.816,"dv_freq":"6197#568#3#0#0#0#0#0#0#0#0#0#0#0#0","dem_table":"422#0#10#0#432|1763#81#133#0#1977|773#277#14#0#1064|587#264#0#0#851|346#183#0#0#529|190#0#0#0#190|108#0#0#0#108|0#0#0#0#0|0#0#0#0#0|0#0#0#1617#1617|4189#805#157#1617#6768","dem_uq":"9#0#1#0#10|29#5#4#0#38|23#5#1#0#29|10#2#0#0#12|7#5#0#0#12|3#0#0#0#3|3#0#0#0#3|0#0#0#0#0|0#0#0#0#0|0#0#0#88#88|84#17#6#88#195","dem_fix_r":"","dem_fix_v":""},{"ver":"4","lc":"eo","alg":"v1","sp":"train","clips":20033,"uq_v":54,"uq_s":9256,"uq_sl":9256,"dur_total":98486.496,"dur_avg":4.916,"dur_med":4.656,"dur_std":1.697,"dur_freq":"0#253#1978#4414#4932#3609#2337#1371#718#312#109#0#0","v_avg":370.981,"v_med":46.0,"v_std":949.674,"v_freq":"0#0#0#0#24#0#10#0#4#9#3#2#0#2#0#0#0#0","s_avg":2.164,"s_med":2.0,"s_std":0.876,"s_freq":"0#2367#3546#2798#545#0#0#0#0#0#0#0#0#0#0#0","uv_sum":40226,"uv_avg":3.0,"uv_med":3.0,"uv_std":0.816,"uv_freq":"0#0#19876#154#3#0#0#0#0#0#0#0#0#0#0","dv_sum":1415,"dv_avg":1.0,"dv_med":1.0,"dv_std":0.816,"dv_freq":"18620#1411#2#0#0#0#0#0#0#0#0#0#0#0#0","dem_table":"276#0#10#0#286|6693#829#10#3554#11086|833#0#14#0#847|5852#404#0#0#6256|224#104#0#0#328|53#0#0#0#53|0#0#0#0#0|0#0#0#0#0|0#0#0#0#0|0#0#0#1177#1177|13931#1337#34#4731#20033","dem_uq":"2#0#1#0#3|8#3#1#2#14|9#0#1#0#10|3#1#0#0#4|1#2#0#0#3|1#0#0#0#1|0#0#0#0#0|0#0#0#0#0|0#0#0#0#0|0#0#0#19#19|24#6#3#21#54","dem_fix_r":"","dem_fix_v":""},{"ver":"4","lc":"eo","alg":"v1","sp":"dev","clips":2545,"uq_v":52,"uq_s":2340,"uq_sl":2340,"dur_total":12613.824,"dur_avg":4.956,"dur_med":4.704,"dur_std":1.653,"dur_freq":"0#24#199#589#642#457#330#170#76#49#9#0#0","v_avg":48.942,"v_med":26.5,"v_std":50.485,"v_freq":"0#0#0#0#3#28#11#3#7#0#0#0#0#0#0#0#0#0","s_avg":1.088,"s_med":1.0,"s_std":0.302,"s_freq":"0#2146#185#7#2#0#0#0#0#0#0#0#0#0#0#0","uv_sum":5107,"uv_avg":3.0,"uv_med":3.0,"uv_std":0.816,"uv_freq":"0#0#2529#15#1#0#0#0#0#0#0#0#0#0#0","dv_sum":258,"dv_avg":1.0,"dv_med":1.0,"dv_std":0.816,"dv_freq":"2289#254#2#0#0#0#0#0#0#0#0#0#0#0#0","dem_table":"35#0#0#0#35|983#64#25#0#1072|190#213#0#0#403|57#152#0#0#209|117#0#0#0#117|19#0#0#0#19|20#0#0#0#20|0#0#0#0#0|0#0#0#0#0|0#0#0#670#670|1421#429#25#670#2545","dem_uq":"2#0#0#0#2|13#2#1#0#16|4#3#0#0#7|2#1#0#0#3|5#0#0#0#5|1#0#0#0#1|1#0#0#0#1|0#0#0#0#0|0#0#0#0#0|0#0#0#17#17|28#6#1#17#52","dem_fix_r":"","dem_fix_v":""},{"ver":"4","lc":"eo","alg":"v1","sp":"test","clips":2569,"uq_v":105,"uq_s":2241,"uq_sl":2241,"dur_total":13617.384,"dur_avg":5.301,"dur_med":5.016,"dur_std":1.604,"dur_freq":"0#4#100#464#699#526#365#239#109#51#12#0#0","v_avg":24.467,"v_med":5.0,"v_std":38.213,"v_freq":"0#5#14#58#4#0#2#22#0#0#0#0#0#0#0#0#0#0","s_avg":1.146,"s_med":1.0,"s_std":0.414,"s_freq":"0#1957#247#31#5#1#0#0#0#0#0#0#0#0#0#0","uv_sum":5175,"uv_avg":2.5,"uv_med":2.5,"uv_std":0.5,"uv_freq":"0#0#2532#37#0#0#0#0#0#0#0#0#0#0#0","dv_sum":160,"dv_avg":1.0,"dv_med":1.0,"dv_std":0.816,"dv_freq":"2410#158#1#0#0#0#0#0#0#0#0#0#0#0#0","dem_table":"111#0#0#0#111|529#3#98#0#630|390#64#0#0#454|312#112#0#0#424|5#79#0#0#84|118#0#0#0#118|88#0#0#0#88|0#0#0#0#0|0#0#0#0#0|0#0#0#660#660|1553#258#98#660#2569","dem_uq":"5#0#0#0#5|13#2#2#0#17|11#2#0#0#13|7#1#0#0#8|1#3#0#0#4|1#0#0#0#1|2#0#0#0#2|0#0#0#0#0|0#0#0#0#0|0#0#0#55#55|40#8#2#55#105","dem_fix_r":"","dem_fix_v":""}]}