{"schema":{"fields":[{"name":"ver","type":"string"},{"name":"lc","type":"string"},{"name":"alg","type":"string"},{"name":"sp","type":"string"},{"name":"clips","type":"integer"},{"name":"uq_v","type":"integer"},{"name":"uq_s","type":"integer"},{"name":"uq_sl","type":"integer"},{"name":"dur_total","type":"number"},{"name":"dur_avg","type":"number"},{"name":"dur_med","type":"number"},{"name":"dur_std","type":"number"},{"name":"dur_freq","type":"string"},{"name":"v_avg","type":"number"},{"name":"v_med","type":"number"},{"name":"v_std","type":"number"},{"name":"v_freq","type":"string"},{"name":"s_avg","type":"number"},{"name":"s_med","type":"number"},{"name":"s_std","type":"number"},{"name":"s_freq","type":"string"},{"name":"uv_sum","type":"integer"},{"name":"uv_avg","type":"number"},{"name":"uv_med","type":"number"},{"name":"uv_std","type":"number"},{"name":"uv_freq","type":"string"},{"name":"dv_sum","type":"integer"},{"name":"dv_avg","type":"number"},{"name":"dv_med","type":"number"},{"name":"dv_std","type":"number"},{"name":"dv_freq","type":"string"},{"name":"dem_table","type":"string"},{"name":"dem_uq","type":"string"},{"name":"dem_fix_r","type":"string"},{"name":"dem_fix_v","type":"string"}],"pandas_version":"1.4.0"},"data":[{"ver":"9.0","lc":"fi","alg":"","sp":"clips","clips":12164,"uq_v":178,"uq_s":5622,"uq_sl":5622,"dur_total":55337.382,"dur_avg":4.549,"dur_med":4.176,"dur_std":1.525,"dur_freq":"0#49#1628#3805#2601#1873#1240#643#220#88#17#0#0","v_avg":68.337,"v_med":10.0,"v_std":355.303,"v_freq":"0#4#4#63#41#22#19#11#7#3#3#0#0#1#0#0#0#0","s_avg":2.164,"s_med":2.0,"s_std":0.413,"s_freq":"0#91#4524#1003#4#0#0#0#0#0#0#0#0#0#0#0","uv_sum":15241,"uv_avg":2.0,"uv_med":2.0,"uv_std":1.414,"uv_freq":"3899#1336#6884#43#2#0#0#0#0#0#0#0#0#0#0","dv_sum":964,"dv_avg":1.0,"dv_med":1.0,"dv_std":0.816,"dv_freq":"11389#586#189#0#0#0#0#0#0#0#0#0#0#0#0","dem_table":"72#0#22#0#94|1015#180#35#0#1230|1298#239#0#0#1537|313#4089#0#0#4402|125#118#0#0#243|0#0#0#0#0|10#0#0#0#10|0#0#0#0#0|0#0#0#0#0|0#0#0#4648#4648|2833#4626#57#4648#12164","dem_uq":"3#0#1#0#4|16#7#2#0#25|11#4#0#0#15|6#2#0#0#8|6#1#0#0#7|0#0#0#0#0|1#0#0#0#1|0#0#0#0#0|0#0#0#0#0|0#0#0#135#135|43#14#3#135#195","dem_fix_r":"0#0#0|799#315#0|966#5#0|0#440#0|15#5#0|0#0#0|0#0#0|0#0#0|0#0#0","dem_fix_v":"0#0#0|3#2#0|6#1#0|0#1#0|3#1#0|0#0#0|0#0#0|0#0#0|0#0#0"},{"ver":"9.0","lc":"fi","alg":"","sp":"validated","clips":6929,"uq_v":124,"uq_s":5508,"uq_sl":5508,"dur_total":31848.652,"dur_avg":4.596,"dur_med":4.248,"dur_std":1.548,"dur_freq":"0#21#893#2142#1476#1080#716#402#127#57#15#0#0","v_avg":55.879,"v_med":10.0,"v_std":206.878,"v_freq":"0#11#6#36#25#14#14#8#6#1#2#1#0#0#0#0#0#0","s_avg":1.258,"s_med":1.0,"s_std":0.44,"s_freq":"0#4092#1411#5#0#0#0#0#0#0#0#0#0#0#0#0","uv_sum":13905,"uv_avg":3.0,"uv_med":3.0,"uv_std":0.816,"uv_freq":"0#0#6884#43#2#0#0#0#0#0#0#0#0#0#0","dv_sum":481,"dv_avg":0.5,"dv_med":0.5,"dv_std":0.5,"dv_freq":"6448#481#0#0#0#0#0#0#0#0#0#0#0#0#0","dem_table":"59#0#21#0#80|717#132#2#0#851|1113#119#0#0#1232|260#1606#0#0#1866|95#0#0#0#95|0#0#0#0#0|0#0#0#0#0|0#0#0#0#0|0#0#0#0#0|0#0#0#2805#2805|2244#1857#23#2805#6929","dem_uq":"2#0#1#0#3|14#5#1#0#20|8#3#0#0#11|5#1#0#0#6|5#0#0#0#5|0#0#0#0#0|0#0#0#0#0|0#0#0#0#0|0#0#0#0#0|0#0#0#91#91|34#9#2#91#136","dem_fix_r":"0#0#0|795#308#0|20#0#0|0#415#0|8#0#0|0#0#0|0#0#0|0#0#0|0#0#0","dem_fix_v":"0#0#0|3#2#0|4#0#0|0#1#0|2#0#0|0#0#0|0#0#0|0#0#0|0#0#0"},{"ver":"9.0","lc":"fi","alg":"","sp":"invalidated","clips":189,"uq_v":51,"uq_s":187,"uq_sl":187,"dur_total":947.079,"dur_avg":5.011,"dur_med":4.536,"dur_std":1.812,"dur_freq":"0#2#18#50#39#21#28#16#12#2#1#0#0","v_avg":3.706,"v_med":1.0,"v_std":5.939,"v_freq":"0#28#12#6#2#3#0#0#0#0#0#0#0#0#0#0#0#0","s_avg":1.011,"s_med":1.0,"s_std":0.103,"s_freq":"0#185#2#0#0#0#0#0#0#0#0#0#0#0#0#0","uv_sum":73,"uv_avg":0.5,"uv_med":0.5,"uv_std":0.5,"uv_freq":"116#73#0#0#0#0#0#0#0#0#0#0#0#0#0","dv_sum":378,"dv_avg":2.0,"dv_med":2.0,"dv_std":0.0,"dv_freq":"0#0#189#0#0#0#0#0#0#0#0#0#0#0#0","dem_table":"3#0#1#0#4|12#18#0#0#30|32#3#0#0#35|5#18#0#0#23|0#0#0#0#0|0#0#0#0#0|0#0#0#0#0|0#0#0#0#0|0#0#0#0#0|0#0#0#97#97|52#39#1#97#189","dem_uq":"1#0#1#0#2|7#2#0#0#9|4#1#0#0#5|5#1#0#0#6|0#0#0#0#0|0#0#0#0#0|0#0#0#0#0|0#0#0#0#0|0#0#0#0#0|0#0#0#31#31|17#4#1#31#53","dem_fix_r":"0#0#0|4#0#0|0#0#0|0#7#0|0#0#0|0#0#0|0#0#0|0#0#0|0#0#0","dem_fix_v":"0#0#0|1#0#0|0#0#0|0#1#0|0#0#0|0#0#0|0#0#0|0#0#0|0#0#0"},{"ver":"9.0","lc":"fi","alg":"","sp":"other","clips":5046,"uq_v":77,"uq_s":4698,"uq_sl":4698,"dur_total":22541.652,"dur_avg":4.467,"dur_med":4.14,"dur_std":1.475,"dur_freq":"0#26#717#1613#1086#772#496#225#81#29#1#0#0","v_avg":65.532,"v_med":6.0,"v_std":299.21,"v_freq":"0#6#4#29#16#7#7#3#3#0#1#0#1#0#0#0#0#0","s_avg":1.074,"s_med":1.0,"s_std":0.262,"s_freq":"0#4350#348#0#0#0#0#0#0#0#0#0#0#0#0#0","uv_sum":1263,"uv_avg":0.5,"uv_med":0.5,"uv_std":0.5,"uv_freq":"3783#1263#0#0#0#0#0#0#0#0#0#0#0#0#0","dv_sum":105,"dv_avg":0.5,"dv_med":0.5,"dv_std":0.5,"dv_freq":"4941#105#0#0#0#0#0#0#0#0#0#0#0#0#0","dem_table":"10#0#0#0#10|286#30#33#0#349|153#117#0#0#270|48#2465#0#0#2513|30#118#0#0#148|0#0#0#0#0|10#0#0#0#10|0#0#0#0#0|0#0#0#0#0|0#0#0#1746#1746|537#2730#33#1746#5046","dem_uq":"1#0#0#0#1|5#2#2#0#9|5#2#0#0#7|2#2#0#0#4|3#1#0#0#4|0#0#0#0#0|1#0#0#0#1|0#0#0#0#0|0#0#0#0#0|0#0#0#57#57|17#7#2#57#83","dem_fix_r":"0#0#0|0#0#0|938#5#0|0#18#0|5#5#0|0#0#0|0#0#0|0#0#0|0#0#0","dem_fix_v":"0#0#0|0#0#0|2#1#0|0#1#0|1#1#0|0#0#0|0#0#0|0#0#0|0#0#0"},{"ver":"9.0","lc":"fi","alg":"s1","sp":"train","clips":2314,"uq_v":3,"uq_s":2314,"uq_sl":2314,"dur_total":10688.136,"dur_avg":4.619,"dur_med":4.248,"dur_std":1.49,"dur_freq":"0#0#269#734#486#372#257#154#30#9#3#0#0","v_avg":771.333,"v_med":881.0,"v_std":226.392,"v_freq":"0#0#0#0#0#0#0#0#0#1#2#0#0#0#0#0#0#0","s_avg":1.0,"s_med":1.0,"s_std":0.0,"s_freq":"0#2314#0#0#0#0#0#0#0#0#0#0#0#0#0#0","uv_sum":4657,"uv_avg":2.5,"uv_med":2.5,"uv_std":0.5,"uv_freq":"0#0#2285#29#0#0#0#0#0#0#0#0#0#0#0","dv_sum":129,"dv_avg":0.5,"dv_med":0.5,"dv_std":0.5,"dv_freq":"2185#129#0#0#0#0#0#0#0#0#0#0#0#0#0","dem_table":"0#0#0#0#0|205#0#0#0#205|452#0#0#0#452|0#782#0#0#782|0#0#0#0#0|0#0#0#0#0|0#0#0#0#0|0#0#0#0#0|0#0#0#0#0|0#0#0#875#875|657#782#0#875#2314","dem_uq":"0#0#0#0#0|1#0#0#0#1|1#0#0#0#1|0#1#0#0#1|0#0#0#0#0|0#0#0#0#0|0#0#0#0#0|0#0#0#0#0|0#0#0#0#0|0#0#0#3#3|2#1#0#3#6","dem_fix_r":"0#0#0|772#0#0|4#0#0|0#99#0|0#0#0|0#0#0|0#0#0|0#0#0|0#0#0","dem_fix_v":"0#0#0|1#0#0|1#0#0|0#1#0|0#0#0|0#0#0|0#0#0|0#0#0|0#0#0"},{"ver":"9.0","lc":"fi","alg":"s1","sp":"dev","clips":1433,"uq_v":10,"uq_s":1433,"uq_sl":1433,"dur_total":6243.84,"dur_avg":4.357,"dur_med":3.96,"dur_std":1.555,"dur_freq":"0#10#261#472#265#197#130#61#26#8#3#0#0","v_avg":143.3,"v_med":128.0,"v_std":56.74,"v_freq":"0#0#0#0#0#0#0#5#5#0#0#0#0#0#0#0#0#0","s_avg":1.0,"s_med":1.0,"s_std":0.0,"s_freq":"0#1433#0#0#0#0#0#0#0#0#0#0#0#0#0#0","uv_sum":2867,"uv_avg":2.5,"uv_med":2.5,"uv_std":0.5,"uv_freq":"0#0#1432#1#0#0#0#0#0#0#0#0#0#0#0","dv_sum":109,"dv_avg":0.5,"dv_med":0.5,"dv_std":0.5,"dv_freq":"1324#109#0#0#0#0#0#0#0#0#0#0#0#0#0","dem_table":"0#0#0#0#0|218#23#0#0#241|484#0#0#0#484|132#0#0#0#132|0#0#0#0#0|0#0#0#0#0|0#0#0#0#0|0#0#0#0#0|0#0#0#0#0|0#0#0#576#576|834#23#0#576#1433","dem_uq":"0#0#0#0#0|2#1#0#0#3|3#0#0#0#3|1#0#0#0#1|0#0#0#0#0|0#0#0#0#0|0#0#0#0#0|0#0#0#0#0|0#0#0#0#0|0#0#0#4#4|6#1#0#4#11","dem_fix_r":"0#0#0|0#226#0|0#0#0|0#0#0|0#0#0|0#0#0|0#0#0|0#0#0|0#0#0","dem_fix_v":"0#0#0|0#1#0|0#0#0|0#0#0|0#0#0|0#0#0|0#0#0|0#0#0|0#0#0"},{"ver":"9.0","lc":"fi","alg":"s1","sp":"test","clips":1761,"uq_v":111,"uq_s":1761,"uq_sl":1761,"dur_total":8509.103,"dur_avg":4.832,"dur_med":4.5,"dur_std":1.671,"dur_freq":"0#4#190#480#404#280#188#122#52#33#8#0#0","v_avg":15.865,"v_med":9.0,"v_std":19.281,"v_freq":"0#11#7#35#26#13#14#5#0#0#0#0#0#0#0#0#0#0","s_avg":1.0,"s_med":1.0,"s_std":0.0,"s_freq":"0#1761#0#0#0#0#0#0#0#0#0#0#0#0#0#0","uv_sum":3536,"uv_avg":3.0,"uv_med":3.0,"uv_std":0.816,"uv_freq":"0#0#1749#10#2#0#0#0#0#0#0#0#0#0#0","dv_sum":148,"dv_avg":0.5,"dv_med":0.5,"dv_std":0.5,"dv_freq":"1613#148#0#0#0#0#0#0#0#0#0#0#0#0#0","dem_table":"58#0#21#0#79|202#106#2#0#310|94#118#0#0#212|100#0#0#0#100|93#0#0#0#93|0#0#0#0#0|0#0#0#0#0|0#0#0#0#0|0#0#0#0#0|0#0#0#967#967|547#224#23#967#1761","dem_uq":"2#0#1#0#3|11#4#1#0#16|4#3#0#0#7|4#0#0#0#4|5#0#0#0#5|0#0#0#0#0|0#0#0#0#0|0#0#0#0#0|0#0#0#0#0|0#0#0#84#84|26#7#2#84#119","dem_fix_r":"0#0#0|10#80#0|15#0#0|0#0#0|7#0#0|0#0#0|0#0#0|0#0#0|0#0#0","dem_fix_v":"0#0#0|2#1#0|3#0#0|0#0#0|2#0#0|0#0#0|0#0#0|0#0#0|0#0#0"},{"ver":"9.0","lc":"fi","alg":"s99","sp":"train","clips":3014,"uq_v":2,"uq_s":3009,"uq_sl":3009,"dur_total":14024.196,"dur_avg":4.653,"dur_med":4.32,"dur_std":1.474,"dur_freq":"0#0#315#953#662#482#346#197#43#12#4#0#0","v_avg":1507.0,"v_med":1507.0,"v_std":514.0,"v_freq":"0#0#0#0#0#0#0#0#0#0#1#1#0#0#0#0#0#0","s_avg":1.002,"s_med":1.0,"s_std":0.041,"s_freq":"0#3004#5#0#0#0#0#0#0#0#0#0#0#0#0#0","uv_sum":6060,"uv_avg":2.5,"uv_med":2.5,"uv_std":0.5,"uv_freq":"0#0#2982#32#0#0#0#0#0#0#0#0#0#0#0","dv_sum":182,"dv_avg":0.5,"dv_med":0.5,"dv_std":0.5,"dv_freq":"2832#182#0#0#0#0#0#0#0#0#0#0#0#0#0","dem_table":"0#0#0#0#0|208#0#0#0#208|0#0#0#0#0|0#1606#0#0#1606|0#0#0#0#0|0#0#0#0#0|0#0#0#0#0|0#0#0#0#0|0#0#0#0#0|0#0#0#1200#1200|208#1606#0#1200#3014","dem_uq":"0#0#0#0#0|1#0#0#0#1|0#0#0#0#0|0#1#0#0#1|0#0#0#0#0|0#0#0#0#0|0#0#0#0#0|0#0#0#0#0|0#0#0#0#0|0#0#0#2#2|1#1#0#2#4","dem_fix_r":"0#0#0|785#0#0|0#0#0|0#415#0|0#0#0|0#0#0|0#0#0|0#0#0|0#0#0","dem_fix_v":"0#0#0|1#0#0|0#0#0|0#1#0|0#0#0|0#0#0|0#0#0|0#0#0|0#0#0"},{"ver":"9.0","lc":"fi","alg":"s99","sp":"dev","clips":1785,"uq_v":8,"uq_s":1691,"uq_sl":1691,"dur_total":7684.788,"dur_avg":4.305,"dur_med":3.936,"dur_std":1.499,"dur_freq":"0#17#322#600#328#258#156#68#25#8#3#0#0","v_avg":223.125,"v_med":160.0,"v_std":119.853,"v_freq":"0#0#0#0#0#0#0#0#6#1#1#0#0#0#0#0#0#0","s_avg":1.056,"s_med":1.0,"s_std":0.229,"s_freq":"0#1597#94#0#0#0#0#0#0#0#0#0#0#0#0#0","uv_sum":3571,"uv_avg":2.5,"uv_med":2.5,"uv_std":0.5,"uv_freq":"0#0#1784#1#0#0#0#0#0#0#0#0#0#0#0","dv_sum":120,"dv_avg":0.5,"dv_med":0.5,"dv_std":0.5,"dv_freq":"1665#120#0#0#0#0#0#0#0#0#0#0#0#0#0","dem_table":"0#0#0#0#0|303#25#0#0#328|904#0#0#0#904|157#0#0#0#157|0#0#0#0#0|0#0#0#0#0|0#0#0#0#0|0#0#0#0#0|0#0#0#0#0|0#0#0#396#396|1364#25#0#396#1785","dem_uq":"0#0#0#0#0|2#1#0#0#3|3#0#0#0#3|1#0#0#0#1|0#0#0#0#0|0#0#0#0#0|0#0#0#0#0|0#0#0#0#0|0#0#0#0#0|0#0#0#3#3|6#1#0#3#10","dem_fix_r":"0#0#0|0#228#0|5#0#0|0#0#0|0#0#0|0#0#0|0#0#0|0#0#0|0#0#0","dem_fix_v":"0#0#0|0#1#0|1#0#0|0#0#0|0#0#0|0#0#0|0#0#0|0#0#0|0#0#0"},{"ver":"9.0","lc":"fi","alg":"s99","sp":"test","clips":2130,"uq_v":114,"uq_s":2084,"uq_sl":2084,"dur_total":10139.668,"dur_avg":4.76,"dur_med":4.428,"dur_std":1.654,"dur_freq":"0#4#256#589#486#340#214#137#59#37#8#0#0","v_avg":18.684,"v_med":9.0,"v_std":24.905,"v_freq":"0#11#6#36#25#14#14#8#0#0#0#0#0#0#0#0#0#0","s_avg":1.022,"s_med":1.0,"s_std":0.147,"s_freq":"0#2038#46#0#0#0#0#0#0#0#0#0#0#0#0#0","uv_sum":4274,"uv_avg":3.0,"uv_med":3.0,"uv_std":0.816,"uv_freq":"0#0#2118#10#2#0#0#0#0#0#0#0#0#0#0","dv_sum":179,"dv_avg":0.5,"dv_med":0.5,"dv_std":0.5,"dv_freq":"1951#179#0#0#0#0#0#0#0#0#0#0#0#0#0","dem_table":"59#0#21#0#80|206#107#2#0#315|209#119#0#0#328|103#0#0#0#103|95#0#0#0#95|0#0#0#0#0|0#0#0#0#0|0#0#0#0#0|0#0#0#0#0|0#0#0#1209#1209|672#226#23#1209#2130","dem_uq":"2#0#1#0#3|11#4#1#0#16|5#3#0#0#8|4#0#0#0#4|5#0#0#0#5|0#0#0#0#0|0#0#0#0#0|0#0#0#0#0|0#0#0#0#0|0#0#0#86#86|27#7#2#86#122","dem_fix_r":"0#0#0|10#80#0|15#0#0|0#0#0|8#0#0|0#0#0|0#0#0|0#0#0|0#0#0","dem_fix_v":"0#0#0|2#1#0|3#0#0|0#0#0|2#0#0|0#0#0|0#0#0|0#0#0|0#0#0"},{"ver":"9.0","lc":"fi","alg":"v1","sp":"train","clips":5519,"uq_v":31,"uq_s":4571,"uq_sl":4571,"dur_total":24979.296,"dur_avg":4.526,"dur_med":4.176,"dur_std":1.498,"dur_freq":"0#17#740#1767#1158#862#552#306#81#28#8#0#0","v_avg":178.032,"v_med":33.0,"v_std":387.723,"v_freq":"0#0#0#4#9#2#1#5#6#1#2#1#0#0#0#0#0#0","s_avg":1.207,"s_med":1.0,"s_std":0.405,"s_freq":"0#3623#948#0#0#0#0#0#0#0#0#0#0#0#0#0","uv_sum":11071,"uv_avg":2.5,"uv_med":2.5,"uv_std":0.5,"uv_freq":"0#0#5486#33#0#0#0#0#0#0#0#0#0#0#0","dv_sum":379,"dv_avg":0.5,"dv_med":0.5,"dv_std":0.5,"dv_freq":"5140#379#0#0#0#0#0#0#0#0#0#0#0#0#0","dem_table":"0#0#0#0#0|544#46#0#0#590|1017#117#0#0#1134|166#1606#0#0#1772|4#0#0#0#4|0#0#0#0#0|0#0#0#0#0|0#0#0#0#0|0#0#0#0#0|0#0#0#2019#2019|1731#1769#0#2019#5519","dem_uq":"0#0#0#0#0|4#3#0#0#7|4#2#0#0#6|2#1#0#0#3|1#0#0#0#1|0#0#0#0#0|0#0#0#0#0|0#0#0#0#0|0#0#0#0#0|0#0#0#20#20|11#6#0#20#37","dem_fix_r":"0#0#0|785#308#0|5#0#0|0#415#0|3#0#0|0#0#0|0#0#0|0#0#0|0#0#0","dem_fix_v":"0#0#0|1#2#0|1#0#0|0#1#0|1#0#0|0#0#0|0#0#0|0#0#0|0#0#0"},{"ver":"9.0","lc":"fi","alg":"v1","sp":"dev","clips":677,"uq_v":31,"uq_s":674,"uq_sl":674,"dur_total":3308.221,"dur_avg":4.887,"dur_med":4.536,"dur_std":1.661,"dur_freq":"0#0#70#183#151#113#74#48#22#13#3#0#0","v_avg":21.839,"v_med":15.0,"v_std":18.921,"v_freq":"0#0#0#0#16#12#0#3#0#0#0#0#0#0#0#0#0#0","s_avg":1.004,"s_med":1.0,"s_std":0.067,"s_freq":"0#671#3#0#0#0#0#0#0#0#0#0#0#0#0#0","uv_sum":1359,"uv_avg":2.5,"uv_med":2.5,"uv_std":0.5,"uv_freq":"0#0#672#5#0#0#0#0#0#0#0#0#0#0#0","dv_sum":54,"dv_avg":0.5,"dv_med":0.5,"dv_std":0.5,"dv_freq":"623#54#0#0#0#0#0#0#0#0#0#0#0#0#0","dem_table":"0#0#21#0#21|61#81#0#0#142|95#0#0#0#95|0#0#0#0#0|20#0#0#0#20|0#0#0#0#0|0#0#0#0#0|0#0#0#0#0|0#0#0#0#0|0#0#0#399#399|176#81#21#399#677","dem_uq":"0#0#1#0#1|4#1#0#0#5|3#0#0#0#3|0#0#0#0#0|1#0#0#0#1|0#0#0#0#0|0#0#0#0#0|0#0#0#0#0|0#0#0#0#0|0#0#0#25#25|8#1#1#25#35","dem_fix_r":"0#0#0|5#0#0|15#0#0|0#0#0|0#0#0|0#0#0|0#0#0|0#0#0|0#0#0","dem_fix_v":"0#0#0|1#0#0|3#0#0|0#0#0|0#0#0|0#0#0|0#0#0|0#0#0|0#0#0"},{"ver":"9.0","lc":"fi","alg":"v1","sp":"test","clips":733,"uq_v":62,"uq_s":730,"uq_sl":730,"dur_total":3561.134,"dur_avg":4.858,"dur_med":4.5,"dur_std":1.74,"dur_freq":"0#4#83#192#167#105#90#48#24#16#4#0#0","v_avg":11.823,"v_med":5.0,"v_std":16.499,"v_freq":"0#11#6#32#0#0#13#0#0#0#0#0#0#0#0#0#0#0","s_avg":1.004,"s_med":1.0,"s_std":0.064,"s_freq":"0#727#3#0#0#0#0#0#0#0#0#0#0#0#0#0","uv_sum":1475,"uv_avg":3.0,"uv_med":3.0,"uv_std":0.816,"uv_freq":"0#0#726#5#2#0#0#0#0#0#0#0#0#0#0","dv_sum":48,"dv_avg":0.5,"dv_med":0.5,"dv_std":0.5,"dv_freq":"685#48#0#0#0#0#0#0#0#0#0#0#0#0#0","dem_table":"59#0#0#0#59|112#5#2#0#119|1#2#0#0#3|94#0#0#0#94|71#0#0#0#71|0#0#0#0#0|0#0#0#0#0|0#0#0#0#0|0#0#0#0#0|0#0#0#387#387|337#7#2#387#733","dem_uq":"2#0#0#0#2|6#1#1#0#8|1#1#0#0#2|3#0#0#0#3|3#0#0#0#3|0#0#0#0#0|0#0#0#0#0|0#0#0#0#0|0#0#0#0#0|0#0#0#46#46|15#2#1#46#64","dem_fix_r":"0#0#0|5#0#0|0#0#0|0#0#0|5#0#0|0#0#0|0#0#0|0#0#0|0#0#0","dem_fix_v":"0#0#0|1#0#0|0#0#0|0#0#0|1#0#0|0#0#0|0#0#0|0#0#0|0#0#0"}]}