{"schema":{"fields":[{"name":"ver","type":"string"},{"name":"lc","type":"string"},{"name":"alg","type":"string"},{"name":"sp","type":"string"},{"name":"clips","type":"number"},{"name":"uq_v","type":"number"},{"name":"uq_s","type":"number"},{"name":"uq_sl","type":"number"},{"name":"dur_total","type":"number"},{"name":"dur_avg","type":"number"},{"name":"dur_med","type":"number"},{"name":"dur_std","type":"number"},{"name":"dur_freq","type":"string"},{"name":"v_avg","type":"number"},{"name":"v_med","type":"number"},{"name":"v_std","type":"number"},{"name":"v_freq","type":"string"},{"name":"s_avg","type":"number"},{"name":"s_med","type":"number"},{"name":"s_std","type":"number"},{"name":"s_freq","type":"string"},{"name":"uv_sum","type":"number"},{"name":"uv_avg","type":"number"},{"name":"uv_med","type":"number"},{"name":"uv_std","type":"number"},{"name":"uv_freq","type":"string"},{"name":"dv_sum","type":"number"},{"name":"dv_avg","type":"number"},{"name":"dv_med","type":"number"},{"name":"dv_std","type":"number"},{"name":"dv_freq","type":"string"},{"name":"dem_table","type":"string"},{"name":"dem_uq","type":"string"},{"name":"dem_fix_r","type":"string"},{"name":"dem_fix_v","type":"string"}],"pandas_version":"1.4.0"},"data":[{"ver":"6.1","lc":"as","alg":"","sp":"clips","clips":535.0,"uq_v":17.0,"uq_s":534.0,"uq_sl":534.0,"dur_total":2835.905,"dur_avg":5.301,"dur_med":5.208,"dur_std":1.502,"dur_freq":"0#15#10#73#138#142#86#47#17#7#0#0#0","v_avg":31.471,"v_med":6.0,"v_std":66.553,"v_freq":"0#1#3#5#4#2#0#1#0#1#0#0#0#0#0#0#0#0","s_avg":1.002,"s_med":1.0,"s_std":0.043,"s_freq":"0#533#1#0#0#0#0#0#0#0#0#0#0#0#0#0","uv_sum":1011.0,"uv_avg":1.0,"uv_med":1.0,"uv_std":0.816,"uv_freq":"28#3#504#0#0#0#0#0#0#0#0#0#0#0#0","dv_sum":73.0,"dv_avg":1.5,"dv_med":1.5,"dv_std":1.118,"dv_freq":"498#6#26#5#0#0#0#0#0#0#0#0#0#0#0","dem_table":"0#0#0#0#0|156#0#0#0#156|45#0#0#0#45|0#0#0#0#0|0#0#0#0#0|0#0#0#0#0|0#0#0#0#0|0#0#0#0#0|0#0#0#0#0|0#0#0#334#334|201#0#0#334#535","dem_uq":"0#0#0#0#0|3#0#0#0#3|3#0#0#0#3|0#0#0#0#0|0#0#0#0#0|0#0#0#0#0|0#0#0#0#0|0#0#0#0#0|0#0#0#0#0|0#0#0#11#11|6#0#0#11#17","dem_fix_r":"","dem_fix_v":""},{"ver":"6.1","lc":"as","alg":"","sp":"validated","clips":504.0,"uq_v":14.0,"uq_s":504.0,"uq_sl":504.0,"dur_total":2719.793,"dur_avg":5.396,"dur_med":5.256,"dur_std":1.363,"dur_freq":"0#0#8#73#134#136#86#46#16#5#0#0#0","v_avg":36.0,"v_med":7.5,"v_std":71.743,"v_freq":"0#1#3#3#3#2#0#1#0#1#0#0#0#0#0#0#0#0","s_avg":1.0,"s_med":1.0,"s_std":0.0,"s_freq":"0#504#0#0#0#0#0#0#0#0#0#0#0#0#0#0","uv_sum":1008.0,"uv_avg":2.0,"uv_med":2.0,"uv_std":0.0,"uv_freq":"0#0#504#0#0#0#0#0#0#0#0#0#0#0#0","dv_sum":6.0,"dv_avg":0.5,"dv_med":0.5,"dv_std":0.5,"dv_freq":"498#6#0#0#0#0#0#0#0#0#0#0#0#0#0","dem_table":"0#0#0#0#0|139#0#0#0#139|39#0#0#0#39|0#0#0#0#0|0#0#0#0#0|0#0#0#0#0|0#0#0#0#0|0#0#0#0#0|0#0#0#0#0|0#0#0#326#326|178#0#0#326#504","dem_uq":"0#0#0#0#0|2#0#0#0#2|2#0#0#0#2|0#0#0#0#0|0#0#0#0#0|0#0#0#0#0|0#0#0#0#0|0#0#0#0#0|0#0#0#0#0|0#0#0#10#10|4#0#0#10#14","dem_fix_r":"","dem_fix_v":""},{"ver":"6.1","lc":"as","alg":"","sp":"invalidated","clips":31.0,"uq_v":10.0,"uq_s":31.0,"uq_sl":31.0,"dur_total":116.112,"dur_avg":3.746,"dur_med":2.424,"dur_std":2.483,"dur_freq":"0#15#2#0#4#6#0#1#1#2#0#0#0","v_avg":3.1,"v_med":1.5,"v_std":4.134,"v_freq":"0#5#3#1#1#0#0#0#0#0#0#0#0#0#0#0#0#0","s_avg":1.0,"s_med":1.0,"s_std":0.0,"s_freq":"0#31#0#0#0#0#0#0#0#0#0#0#0#0#0#0","uv_sum":3.0,"uv_avg":0.5,"uv_med":0.5,"uv_std":0.5,"uv_freq":"28#3#0#0#0#0#0#0#0#0#0#0#0#0#0","dv_sum":67.0,"dv_avg":2.5,"dv_med":2.5,"dv_std":0.5,"dv_freq":"0#0#26#5#0#0#0#0#0#0#0#0#0#0#0","dem_table":"0#0#0#0#0|17#0#0#0#17|6#0#0#0#6|0#0#0#0#0|0#0#0#0#0|0#0#0#0#0|0#0#0#0#0|0#0#0#0#0|0#0#0#0#0|0#0#0#8#8|23#0#0#8#31","dem_uq":"0#0#0#0#0|2#0#0#0#2|2#0#0#0#2|0#0#0#0#0|0#0#0#0#0|0#0#0#0#0|0#0#0#0#0|0#0#0#0#0|0#0#0#0#0|0#0#0#6#6|4#0#0#6#10","dem_fix_r":"","dem_fix_v":""},{"ver":"6.1","lc":"as","alg":"","sp":"other","clips":null,"uq_v":null,"uq_s":null,"uq_sl":null,"dur_total":null,"dur_avg":null,"dur_med":null,"dur_std":null,"dur_freq":null,"v_avg":null,"v_med":null,"v_std":null,"v_freq":null,"s_avg":null,"s_med":null,"s_std":null,"s_freq":null,"uv_sum":null,"uv_avg":null,"uv_med":null,"uv_std":null,"uv_freq":null,"dv_sum":null,"dv_avg":null,"dv_med":null,"dv_std":null,"dv_freq":null,"dem_table":null,"dem_uq":null,"dem_fix_r":null,"dem_fix_v":null},{"ver":"6.1","lc":"as","alg":"s1","sp":"train","clips":270.0,"uq_v":1.0,"uq_s":270.0,"uq_sl":270.0,"dur_total":1414.92,"dur_avg":5.24,"dur_med":5.136,"dur_std":1.198,"dur_freq":"0#0#2#45#75#77#48#20#2#1#0#0#0","v_avg":270.0,"v_med":270.0,"v_std":0.0,"v_freq":"0#0#0#0#0#0#0#0#0#1#0#0#0#0#0#0#0#0","s_avg":1.0,"s_med":1.0,"s_std":0.0,"s_freq":"0#270#0#0#0#0#0#0#0#0#0#0#0#0#0#0","uv_sum":540.0,"uv_avg":2.0,"uv_med":2.0,"uv_std":0.0,"uv_freq":"0#0#270#0#0#0#0#0#0#0#0#0#0#0#0","dv_sum":1.0,"dv_avg":0.5,"dv_med":0.5,"dv_std":0.5,"dv_freq":"269#1#0#0#0#0#0#0#0#0#0#0#0#0#0","dem_table":"0#0#0#0#0|0#0#0#0#0|0#0#0#0#0|0#0#0#0#0|0#0#0#0#0|0#0#0#0#0|0#0#0#0#0|0#0#0#0#0|0#0#0#0#0|0#0#0#270#270|0#0#0#270#270","dem_uq":"0#0#0#0#0|0#0#0#0#0|0#0#0#0#0|0#0#0#0#0|0#0#0#0#0|0#0#0#0#0|0#0#0#0#0|0#0#0#0#0|0#0#0#0#0|0#0#0#1#1|0#0#0#1#1","dem_fix_r":"","dem_fix_v":""},{"ver":"6.1","lc":"as","alg":"s1","sp":"dev","clips":124.0,"uq_v":1.0,"uq_s":124.0,"uq_sl":124.0,"dur_total":677.784,"dur_avg":5.466,"dur_med":5.364,"dur_std":1.385,"dur_freq":"0#0#1#20#31#32#25#6#9#0#0#0#0","v_avg":124.0,"v_med":124.0,"v_std":0.0,"v_freq":"0#0#0#0#0#0#0#1#0#0#0#0#0#0#0#0#0#0","s_avg":1.0,"s_med":1.0,"s_std":0.0,"s_freq":"0#124#0#0#0#0#0#0#0#0#0#0#0#0#0#0","uv_sum":248.0,"uv_avg":2.0,"uv_med":2.0,"uv_std":0.0,"uv_freq":"0#0#124#0#0#0#0#0#0#0#0#0#0#0#0","dv_sum":1.0,"dv_avg":0.5,"dv_med":0.5,"dv_std":0.5,"dv_freq":"123#1#0#0#0#0#0#0#0#0#0#0#0#0#0","dem_table":"0#0#0#0#0|124#0#0#0#124|0#0#0#0#0|0#0#0#0#0|0#0#0#0#0|0#0#0#0#0|0#0#0#0#0|0#0#0#0#0|0#0#0#0#0|0#0#0#0#0|124#0#0#0#124","dem_uq":"0#0#0#0#0|1#0#0#0#1|0#0#0#0#0|0#0#0#0#0|0#0#0#0#0|0#0#0#0#0|0#0#0#0#0|0#0#0#0#0|0#0#0#0#0|0#0#0#0#0|1#0#0#0#1","dem_fix_r":"","dem_fix_v":""},{"ver":"6.1","lc":"as","alg":"s1","sp":"test","clips":110.0,"uq_v":12.0,"uq_s":110.0,"uq_sl":110.0,"dur_total":627.089,"dur_avg":5.701,"dur_med":5.508,"dur_std":1.632,"dur_freq":"0#0#5#8#28#27#13#20#5#4#0#0#0","v_avg":9.167,"v_med":5.0,"v_std":8.745,"v_freq":"0#1#3#3#3#2#0#0#0#0#0#0#0#0#0#0#0#0","s_avg":1.0,"s_med":1.0,"s_std":0.0,"s_freq":"0#110#0#0#0#0#0#0#0#0#0#0#0#0#0#0","uv_sum":220.0,"uv_avg":2.0,"uv_med":2.0,"uv_std":0.0,"uv_freq":"0#0#110#0#0#0#0#0#0#0#0#0#0#0#0","dv_sum":4.0,"dv_avg":0.5,"dv_med":0.5,"dv_std":0.5,"dv_freq":"106#4#0#0#0#0#0#0#0#0#0#0#0#0#0","dem_table":"0#0#0#0#0|15#0#0#0#15|39#0#0#0#39|0#0#0#0#0|0#0#0#0#0|0#0#0#0#0|0#0#0#0#0|0#0#0#0#0|0#0#0#0#0|0#0#0#56#56|54#0#0#56#110","dem_uq":"0#0#0#0#0|1#0#0#0#1|2#0#0#0#2|0#0#0#0#0|0#0#0#0#0|0#0#0#0#0|0#0#0#0#0|0#0#0#0#0|0#0#0#0#0|0#0#0#9#9|3#0#0#9#12","dem_fix_r":"","dem_fix_v":""},{"ver":"6.1","lc":"as","alg":"s99","sp":"train","clips":270.0,"uq_v":1.0,"uq_s":270.0,"uq_sl":270.0,"dur_total":1414.92,"dur_avg":5.24,"dur_med":5.136,"dur_std":1.198,"dur_freq":"0#0#2#45#75#77#48#20#2#1#0#0#0","v_avg":270.0,"v_med":270.0,"v_std":0.0,"v_freq":"0#0#0#0#0#0#0#0#0#1#0#0#0#0#0#0#0#0","s_avg":1.0,"s_med":1.0,"s_std":0.0,"s_freq":"0#270#0#0#0#0#0#0#0#0#0#0#0#0#0#0","uv_sum":540.0,"uv_avg":2.0,"uv_med":2.0,"uv_std":0.0,"uv_freq":"0#0#270#0#0#0#0#0#0#0#0#0#0#0#0","dv_sum":1.0,"dv_avg":0.5,"dv_med":0.5,"dv_std":0.5,"dv_freq":"269#1#0#0#0#0#0#0#0#0#0#0#0#0#0","dem_table":"0#0#0#0#0|0#0#0#0#0|0#0#0#0#0|0#0#0#0#0|0#0#0#0#0|0#0#0#0#0|0#0#0#0#0|0#0#0#0#0|0#0#0#0#0|0#0#0#270#270|0#0#0#270#270","dem_uq":"0#0#0#0#0|0#0#0#0#0|0#0#0#0#0|0#0#0#0#0|0#0#0#0#0|0#0#0#0#0|0#0#0#0#0|0#0#0#0#0|0#0#0#0#0|0#0#0#1#1|0#0#0#1#1","dem_fix_r":"","dem_fix_v":""},{"ver":"6.1","lc":"as","alg":"s99","sp":"dev","clips":124.0,"uq_v":1.0,"uq_s":124.0,"uq_sl":124.0,"dur_total":677.784,"dur_avg":5.466,"dur_med":5.364,"dur_std":1.385,"dur_freq":"0#0#1#20#31#32#25#6#9#0#0#0#0","v_avg":124.0,"v_med":124.0,"v_std":0.0,"v_freq":"0#0#0#0#0#0#0#1#0#0#0#0#0#0#0#0#0#0","s_avg":1.0,"s_med":1.0,"s_std":0.0,"s_freq":"0#124#0#0#0#0#0#0#0#0#0#0#0#0#0#0","uv_sum":248.0,"uv_avg":2.0,"uv_med":2.0,"uv_std":0.0,"uv_freq":"0#0#124#0#0#0#0#0#0#0#0#0#0#0#0","dv_sum":1.0,"dv_avg":0.5,"dv_med":0.5,"dv_std":0.5,"dv_freq":"123#1#0#0#0#0#0#0#0#0#0#0#0#0#0","dem_table":"0#0#0#0#0|124#0#0#0#124|0#0#0#0#0|0#0#0#0#0|0#0#0#0#0|0#0#0#0#0|0#0#0#0#0|0#0#0#0#0|0#0#0#0#0|0#0#0#0#0|124#0#0#0#124","dem_uq":"0#0#0#0#0|1#0#0#0#1|0#0#0#0#0|0#0#0#0#0|0#0#0#0#0|0#0#0#0#0|0#0#0#0#0|0#0#0#0#0|0#0#0#0#0|0#0#0#0#0|1#0#0#0#1","dem_fix_r":"","dem_fix_v":""},{"ver":"6.1","lc":"as","alg":"s99","sp":"test","clips":110.0,"uq_v":12.0,"uq_s":110.0,"uq_sl":110.0,"dur_total":627.089,"dur_avg":5.701,"dur_med":5.508,"dur_std":1.632,"dur_freq":"0#0#5#8#28#27#13#20#5#4#0#0#0","v_avg":9.167,"v_med":5.0,"v_std":8.745,"v_freq":"0#1#3#3#3#2#0#0#0#0#0#0#0#0#0#0#0#0","s_avg":1.0,"s_med":1.0,"s_std":0.0,"s_freq":"0#110#0#0#0#0#0#0#0#0#0#0#0#0#0#0","uv_sum":220.0,"uv_avg":2.0,"uv_med":2.0,"uv_std":0.0,"uv_freq":"0#0#110#0#0#0#0#0#0#0#0#0#0#0#0","dv_sum":4.0,"dv_avg":0.5,"dv_med":0.5,"dv_std":0.5,"dv_freq":"106#4#0#0#0#0#0#0#0#0#0#0#0#0#0","dem_table":"0#0#0#0#0|15#0#0#0#15|39#0#0#0#39|0#0#0#0#0|0#0#0#0#0|0#0#0#0#0|0#0#0#0#0|0#0#0#0#0|0#0#0#0#0|0#0#0#56#56|54#0#0#56#110","dem_uq":"0#0#0#0#0|1#0#0#0#1|2#0#0#0#2|0#0#0#0#0|0#0#0#0#0|0#0#0#0#0|0#0#0#0#0|0#0#0#0#0|0#0#0#0#0|0#0#0#9#9|3#0#0#9#12","dem_fix_r":"","dem_fix_v":""},{"ver":"6.1","lc":"as","alg":"v1","sp":"train","clips":447.0,"uq_v":4.0,"uq_s":447.0,"uq_sl":447.0,"dur_total":2377.385,"dur_avg":5.319,"dur_med":5.184,"dur_std":1.312,"dur_freq":"0#0#8#69#119#125#75#37#12#2#0#0#0","v_avg":111.75,"v_med":76.5,"v_std":99.675,"v_freq":"0#0#0#0#0#2#0#1#0#1#0#0#0#0#0#0#0#0","s_avg":1.0,"s_med":1.0,"s_std":0.0,"s_freq":"0#447#0#0#0#0#0#0#0#0#0#0#0#0#0#0","uv_sum":894.0,"uv_avg":2.0,"uv_med":2.0,"uv_std":0.0,"uv_freq":"0#0#447#0#0#0#0#0#0#0#0#0#0#0#0","dv_sum":3.0,"dv_avg":0.5,"dv_med":0.5,"dv_std":0.5,"dv_freq":"444#3#0#0#0#0#0#0#0#0#0#0#0#0#0","dem_table":"0#0#0#0#0|124#0#0#0#124|29#0#0#0#29|0#0#0#0#0|0#0#0#0#0|0#0#0#0#0|0#0#0#0#0|0#0#0#0#0|0#0#0#0#0|0#0#0#294#294|153#0#0#294#447","dem_uq":"0#0#0#0#0|1#0#0#0#1|1#0#0#0#1|0#0#0#0#0|0#0#0#0#0|0#0#0#0#0|0#0#0#0#0|0#0#0#0#0|0#0#0#0#0|0#0#0#2#2|2#0#0#2#4","dem_fix_r":"","dem_fix_v":""},{"ver":"6.1","lc":"as","alg":"v1","sp":"dev","clips":35.0,"uq_v":3.0,"uq_s":35.0,"uq_sl":35.0,"dur_total":203.016,"dur_avg":5.8,"dur_med":5.664,"dur_std":1.419,"dur_freq":"0#0#0#3#9#9#7#5#1#1#0#0#0","v_avg":11.667,"v_med":10.0,"v_std":2.357,"v_freq":"0#0#0#0#3#0#0#0#0#0#0#0#0#0#0#0#0#0","s_avg":1.0,"s_med":1.0,"s_std":0.0,"s_freq":"0#35#0#0#0#0#0#0#0#0#0#0#0#0#0#0","uv_sum":70.0,"uv_avg":2.0,"uv_med":2.0,"uv_std":0.0,"uv_freq":"0#0#35#0#0#0#0#0#0#0#0#0#0#0#0","dv_sum":2.0,"dv_avg":0.5,"dv_med":0.5,"dv_std":0.5,"dv_freq":"33#2#0#0#0#0#0#0#0#0#0#0#0#0#0","dem_table":"0#0#0#0#0|15#0#0#0#15|10#0#0#0#10|0#0#0#0#0|0#0#0#0#0|0#0#0#0#0|0#0#0#0#0|0#0#0#0#0|0#0#0#0#0|0#0#0#10#10|25#0#0#10#35","dem_uq":"0#0#0#0#0|1#0#0#0#1|1#0#0#0#1|0#0#0#0#0|0#0#0#0#0|0#0#0#0#0|0#0#0#0#0|0#0#0#0#0|0#0#0#0#0|0#0#0#1#1|2#0#0#1#3","dem_fix_r":"","dem_fix_v":""},{"ver":"6.1","lc":"as","alg":"v1","sp":"test","clips":22.0,"uq_v":7.0,"uq_s":22.0,"uq_sl":22.0,"dur_total":139.392,"dur_avg":6.336,"dur_med":6.444,"dur_std":1.759,"dur_freq":"0#0#0#1#6#2#4#4#3#2#0#0#0","v_avg":3.143,"v_med":3.0,"v_std":1.457,"v_freq":"0#1#3#3#0#0#0#0#0#0#0#0#0#0#0#0#0#0","s_avg":1.0,"s_med":1.0,"s_std":0.0,"s_freq":"0#22#0#0#0#0#0#0#0#0#0#0#0#0#0#0","uv_sum":44.0,"uv_avg":2.0,"uv_med":2.0,"uv_std":0.0,"uv_freq":"0#0#22#0#0#0#0#0#0#0#0#0#0#0#0","dv_sum":1.0,"dv_avg":0.5,"dv_med":0.5,"dv_std":0.5,"dv_freq":"21#1#0#0#0#0#0#0#0#0#0#0#0#0#0","dem_table":"0#0#0#0#0|0#0#0#0#0|0#0#0#0#0|0#0#0#0#0|0#0#0#0#0|0#0#0#0#0|0#0#0#0#0|0#0#0#0#0|0#0#0#0#0|0#0#0#22#22|0#0#0#22#22","dem_uq":"0#0#0#0#0|0#0#0#0#0|0#0#0#0#0|0#0#0#0#0|0#0#0#0#0|0#0#0#0#0|0#0#0#0#0|0#0#0#0#0|0#0#0#0#0|0#0#0#7#7|0#0#0#7#7","dem_fix_r":"","dem_fix_v":""}]}